{
  "brand": {
    "brand": "GSBIO",
    "links": [
      "http://www.gsbio.cn/ProductDetail/8699780.html"
    ],
    "brandId": ["CP5000"]
  },
  "wells": {
    "A1": {
      "x": 14.1,
      "y": 74.05,
      "z": 1.5,
      "depth": 14.6,
      "shape": "circular",
      "diameter": 5.66,
      "totalLiquidVolume": 100
    },
    "A2": {
      "x": 23.1,
      "y": 74.05,
      "z": 1.5,
      "depth": 14.6,
      "shape": "circular",
      "diameter": 5.66,
      "totalLiquidVolume": 100
    },
    "A3": {
      "x": 32.1,
      "y": 74.05,
      "z": 1.5,
      "depth": 14.6,
      "shape": "circular",
      "diameter": 5.66,
      "totalLiquidVolume": 100
    },
    "A4": {
      "x": 41.1,
      "y": 74.05,
      "z": 1.5,
      "depth": 14.6,
      "shape": "circular",
      "diameter": 5.66,
      "totalLiquidVolume": 100
    },
    "A5": {
      "x": 50.1,
      "y": 74.05,
      "z": 1.5,
      "depth": 14.6,
      "shape": "circular",
      "diameter": 5.66,
      "totalLiquidVolume": 100
    },
    "A6": {
      "x": 59.1,
      "y": 74.05,
      "z": 1.5,
      "depth": 14.6,
      "shape": "circular",
      "diameter": 5.66,
      "totalLiquidVolume": 100
    },
    "A7": {
      "x": 68.1,
      "y": 74.05,
      "z": 1.5,
      "depth": 14.6,
      "shape": "circular",
      "diameter": 5.66,
      "totalLiquidVolume": 100
    },
    "A8": {
      "x": 77.1,
      "y": 74.05,
      "z": 1.5,
      "depth": 14.6,
      "shape": "circular",
      "diameter": 5.66,
      "totalLiquidVolume": 100
    },
    "A9": {
      "x": 86.1,
      "y": 74.05,
      "z": 1.5,
      "depth": 14.6,
      "shape": "circular",
      "diameter": 5.66,
      "totalLiquidVolume": 100
    },
    "B1": {
      "x": 14.1,
      "y": 65.05,
      "z": 1.5,
      "depth": 14.6,
      "shape": "circular",
      "diameter": 5.66,
      "totalLiquidVolume": 100
    },
    "B2": {
      "x": 23.1,
      "y": 65.05,
      "z": 1.5,
      "depth": 14.6,
      "shape": "circular",
      "diameter": 5.66,
      "totalLiquidVolume": 100
    },
    "B3": {
      "x": 32.1,
      "y": 65.05,
      "z": 1.5,
      "depth": 14.6,
      "shape": "circular",
      "diameter": 5.66,
      "totalLiquidVolume": 100
    },
    "B4": {
      "x": 41.1,
      "y": 65.05,
      "z": 1.5,
      "depth": 14.6,
      "shape": "circular",
      "diameter": 5.66,
      "totalLiquidVolume": 100
    },
    "B5": {
      "x": 50.1,
      "y": 65.05,
      "z": 1.5,
      "depth": 14.6,
      "shape": "circular",
      "diameter": 5.66,
      "totalLiquidVolume": 100
    },
    "B6": {
      "x": 59.1,
      "y": 65.05,
      "z": 1.5,
      "depth": 14.6,
      "shape": "circular",
      "diameter": 5.66,
      "totalLiquidVolume": 100
    },
    "B7": {
      "x": 68.1,
      "y": 65.05,
      "z": 1.5,
      "depth": 14.6,
      "shape": "circular",
      "diameter": 5.66,
      "totalLiquidVolume": 100
    },
    "B8": {
      "x": 77.1,
      "y": 65.05,
      "z": 1.5,
      "depth": 14.6,
      "shape": "circular",
      "diameter": 5.66,
      "totalLiquidVolume": 100
    },
    "B9": {
      "x": 86.1,
      "y": 65.05,
      "z": 1.5,
      "depth": 14.6,
      "shape": "circular",
      "diameter": 5.66,
      "totalLiquidVolume": 100
    },
    "C1": {
      "x": 14.1,
      "y": 56.05,
      "z": 1.5,
      "depth": 14.6,
      "shape": "circular",
      "diameter": 5.66,
      "totalLiquidVolume": 100
    },
    "C2": {
      "x": 23.1,
      "y": 56.05,
      "z": 1.5,
      "depth": 14.6,
      "shape": "circular",
      "diameter": 5.66,
      "totalLiquidVolume": 100
    },
    "C3": {
      "x": 32.1,
      "y": 56.05,
      "z": 1.5,
      "depth": 14.6,
      "shape": "circular",
      "diameter": 5.66,
      "totalLiquidVolume": 100
    },
    "C4": {
      "x": 41.1,
      "y": 56.05,
      "z": 1.5,
      "depth": 14.6,
      "shape": "circular",
      "diameter": 5.66,
      "totalLiquidVolume": 100
    },
    "C5": {
      "x": 50.1,
      "y": 56.05,
      "z": 1.5,
      "depth": 14.6,
      "shape": "circular",
      "diameter": 5.66,
      "totalLiquidVolume": 100
    },
    "C6": {
      "x": 59.1,
      "y": 56.05,
      "z": 1.5,
      "depth": 14.6,
      "shape": "circular",
      "diameter": 5.66,
      "totalLiquidVolume": 100
    },
    "C7": {
      "x": 68.1,
      "y": 56.05,
      "z": 1.5,
      "depth": 14.6,
      "shape": "circular",
      "diameter": 5.66,
      "totalLiquidVolume": 100
    },
    "C8": {
      "x": 77.1,
      "y": 56.05,
      "z": 1.5,
      "depth": 14.6,
      "shape": "circular",
      "diameter": 5.66,
      "totalLiquidVolume": 100
    },
    "C9": {
      "x": 86.1,
      "y": 56.05,
      "z": 1.5,
      "depth": 14.6,
      "shape": "circular",
      "diameter": 5.66,
      "totalLiquidVolume": 100
    },
    "D1": {
      "x": 14.1,
      "y": 47.05,
      "z": 1.5,
      "depth": 14.6,
      "shape": "circular",
      "diameter": 5.66,
      "totalLiquidVolume": 100
    },
    "D2": {
      "x": 23.1,
      "y": 47.05,
      "z": 1.5,
      "depth": 14.6,
      "shape": "circular",
      "diameter": 5.66,
      "totalLiquidVolume": 100
    },
    "D3": {
      "x": 32.1,
      "y": 47.05,
      "z": 1.5,
      "depth": 14.6,
      "shape": "circular",
      "diameter": 5.66,
      "totalLiquidVolume": 100
    },
    "D4": {
      "x": 41.1,
      "y": 47.05,
      "z": 1.5,
      "depth": 14.6,
      "shape": "circular",
      "diameter": 5.66,
      "totalLiquidVolume": 100
    },
    "D5": {
      "x": 50.1,
      "y": 47.05,
      "z": 1.5,
      "depth": 14.6,
      "shape": "circular",
      "diameter": 5.66,
      "totalLiquidVolume": 100
    },
    "D6": {
      "x": 59.1,
      "y": 47.05,
      "z": 1.5,
      "depth": 14.6,
      "shape": "circular",
      "diameter": 5.66,
      "totalLiquidVolume": 100
    },
    "D7": {
      "x": 68.1,
      "y": 47.05,
      "z": 1.5,
      "depth": 14.6,
      "shape": "circular",
      "diameter": 5.66,
      "totalLiquidVolume": 100
    },
    "D8": {
      "x": 77.1,
      "y": 47.05,
      "z": 1.5,
      "depth": 14.6,
      "shape": "circular",
      "diameter": 5.66,
      "totalLiquidVolume": 100
    },
    "D9": {
      "x": 86.1,
      "y": 47.05,
      "z": 1.5,
      "depth": 14.6,
      "shape": "circular",
      "diameter": 5.66,
      "totalLiquidVolume": 100
    },
    "E1": {
      "x": 14.1,
      "y": 38.05,
      "z": 1.5,
      "depth": 14.6,
      "shape": "circular",
      "diameter": 5.66,
      "totalLiquidVolume": 100
    },
    "E2": {
      "x": 23.1,
      "y": 38.05,
      "z": 1.5,
      "depth": 14.6,
      "shape": "circular",
      "diameter": 5.66,
      "totalLiquidVolume": 100
    },
    "E3": {
      "x": 32.1,
      "y": 38.05,
      "z": 1.5,
      "depth": 14.6,
      "shape": "circular",
      "diameter": 5.66,
      "totalLiquidVolume": 100
    },
    "E4": {
      "x": 41.1,
      "y": 38.05,
      "z": 1.5,
      "depth": 14.6,
      "shape": "circular",
      "diameter": 5.66,
      "totalLiquidVolume": 100
    },
    "E5": {
      "x": 50.1,
      "y": 38.05,
      "z": 1.5,
      "depth": 14.6,
      "shape": "circular",
      "diameter": 5.66,
      "totalLiquidVolume": 100
    },
    "E6": {
      "x": 59.1,
      "y": 38.05,
      "z": 1.5,
      "depth": 14.6,
      "shape": "circular",
      "diameter": 5.66,
      "totalLiquidVolume": 100
    },
    "E7": {
      "x": 68.1,
      "y": 38.05,
      "z": 1.5,
      "depth": 14.6,
      "shape": "circular",
      "diameter": 5.66,
      "totalLiquidVolume": 100
    },
    "E8": {
      "x": 77.1,
      "y": 38.05,
      "z": 1.5,
      "depth": 14.6,
      "shape": "circular",
      "diameter": 5.66,
      "totalLiquidVolume": 100
    },
    "E9": {
      "x": 86.1,
      "y": 38.05,
      "z": 1.5,
      "depth": 14.6,
      "shape": "circular",
      "diameter": 5.66,
      "totalLiquidVolume": 100
    },
    "F1": {
      "x": 14.1,
      "y": 29.05,
      "z": 1.5,
      "depth": 14.6,
      "shape": "circular",
      "diameter": 5.66,
      "totalLiquidVolume": 100
    },
    "F2": {
      "x": 23.1,
      "y": 29.05,
      "z": 1.5,
      "depth": 14.6,
      "shape": "circular",
      "diameter": 5.66,
      "totalLiquidVolume": 100
    },
    "F3": {
      "x": 32.1,
      "y": 29.05,
      "z": 1.5,
      "depth": 14.6,
      "shape": "circular",
      "diameter": 5.66,
      "totalLiquidVolume": 100
    },
    "F4": {
      "x": 41.1,
      "y": 29.05,
      "z": 1.5,
      "depth": 14.6,
      "shape": "circular",
      "diameter": 5.66,
      "totalLiquidVolume": 100
    },
    "F5": {
      "x": 50.1,
      "y": 29.05,
      "z": 1.5,
      "depth": 14.6,
      "shape": "circular",
      "diameter": 5.66,
      "totalLiquidVolume": 100
    },
    "F6": {
      "x": 59.1,
      "y": 29.05,
      "z": 1.5,
      "depth": 14.6,
      "shape": "circular",
      "diameter": 5.66,
      "totalLiquidVolume": 100
    },
    "F7": {
      "x": 68.1,
      "y": 29.05,
      "z": 1.5,
      "depth": 14.6,
      "shape": "circular",
      "diameter": 5.66,
      "totalLiquidVolume": 100
    },
    "F8": {
      "x": 77.1,
      "y": 29.05,
      "z": 1.5,
      "depth": 14.6,
      "shape": "circular",
      "diameter": 5.66,
      "totalLiquidVolume": 100
    },
    "F9": {
      "x": 86.1,
      "y": 29.05,
      "z": 1.5,
      "depth": 14.6,
      "shape": "circular",
      "diameter": 5.66,
      "totalLiquidVolume": 100
    },
    "G1": {
      "x": 14.1,
      "y": 20.05,
      "z": 1.5,
      "depth": 14.6,
      "shape": "circular",
      "diameter": 5.66,
      "totalLiquidVolume": 100
    },
    "G2": {
      "x": 23.1,
      "y": 20.05,
      "z": 1.5,
      "depth": 14.6,
      "shape": "circular",
      "diameter": 5.66,
      "totalLiquidVolume": 100
    },
    "G3": {
      "x": 32.1,
      "y": 20.05,
      "z": 1.5,
      "depth": 14.6,
      "shape": "circular",
      "diameter": 5.66,
      "totalLiquidVolume": 100
    },
    "G4": {
      "x": 41.1,
      "y": 20.05,
      "z": 1.5,
      "depth": 14.6,
      "shape": "circular",
      "diameter": 5.66,
      "totalLiquidVolume": 100
    },
    "G5": {
      "x": 50.1,
      "y": 20.05,
      "z": 1.5,
      "depth": 14.6,
      "shape": "circular",
      "diameter": 5.66,
      "totalLiquidVolume": 100
    },
    "G6": {
      "x": 59.1,
      "y": 20.05,
      "z": 1.5,
      "depth": 14.6,
      "shape": "circular",
      "diameter": 5.66,
      "totalLiquidVolume": 100
    },
    "G7": {
      "x": 68.1,
      "y": 20.05,
      "z": 1.5,
      "depth": 14.6,
      "shape": "circular",
      "diameter": 5.66,
      "totalLiquidVolume": 100
    },
    "G8": {
      "x": 77.1,
      "y": 20.05,
      "z": 1.5,
      "depth": 14.6,
      "shape": "circular",
      "diameter": 5.66,
      "totalLiquidVolume": 100
    },
    "G9": {
      "x": 86.1,
      "y": 20.05,
      "z": 1.5,
      "depth": 14.6,
      "shape": "circular",
      "diameter": 5.66,
      "totalLiquidVolume": 100
    },
    "H1": {
      "x": 14.1,
      "y": 11.05,
      "z": 1.5,
      "depth": 14.6,
      "shape": "circular",
      "diameter": 5.66,
      "totalLiquidVolume": 100
    },
    "H2": {
      "x": 23.1,
      "y": 11.05,
      "z": 1.5,
      "depth": 14.6,
      "shape": "circular",
      "diameter": 5.66,
      "totalLiquidVolume": 100
    },
    "H3": {
      "x": 32.1,
      "y": 11.05,
      "z": 1.5,
      "depth": 14.6,
      "shape": "circular",
      "diameter": 5.66,
      "totalLiquidVolume": 100
    },
    "H4": {
      "x": 41.1,
      "y": 11.05,
      "z": 1.5,
      "depth": 14.6,
      "shape": "circular",
      "diameter": 5.66,
      "totalLiquidVolume": 100
    },
    "H5": {
      "x": 50.1,
      "y": 11.05,
      "z": 1.5,
      "depth": 14.6,
      "shape": "circular",
      "diameter": 5.66,
      "totalLiquidVolume": 100
    },
    "H6": {
      "x": 59.1,
      "y": 11.05,
      "z": 1.5,
      "depth": 14.6,
      "shape": "circular",
      "diameter": 5.66,
      "totalLiquidVolume": 100
    },
    "H7": {
      "x": 68.1,
      "y": 11.05,
      "z": 1.5,
      "depth": 14.6,
      "shape": "circular",
      "diameter": 5.66,
      "totalLiquidVolume": 100
    },
    "H8": {
      "x": 77.1,
      "y": 11.05,
      "z": 1.5,
      "depth": 14.6,
      "shape": "circular",
      "diameter": 5.66,
      "totalLiquidVolume": 100
    },
    "H9": {
      "x": 86.1,
      "y": 11.05,
      "z": 1.5,
      "depth": 14.6,
      "shape": "circular",
      "diameter": 5.66,
      "totalLiquidVolume": 100
    },
    "A10": {
      "x": 95.1,
      "y": 74.05,
      "z": 1.5,
      "depth": 14.6,
      "shape": "circular",
      "diameter": 5.66,
      "totalLiquidVolume": 100
    },
    "A11": {
      "x": 104.1,
      "y": 74.05,
      "z": 1.5,
      "depth": 14.6,
      "shape": "circular",
      "diameter": 5.66,
      "totalLiquidVolume": 100
    },
    "A12": {
      "x": 113.1,
      "y": 74.05,
      "z": 1.5,
      "depth": 14.6,
      "shape": "circular",
      "diameter": 5.66,
      "totalLiquidVolume": 100
    },
    "B10": {
      "x": 95.1,
      "y": 65.05,
      "z": 1.5,
      "depth": 14.6,
      "shape": "circular",
      "diameter": 5.66,
      "totalLiquidVolume": 100
    },
    "B11": {
      "x": 104.1,
      "y": 65.05,
      "z": 1.5,
      "depth": 14.6,
      "shape": "circular",
      "diameter": 5.66,
      "totalLiquidVolume": 100
    },
    "B12": {
      "x": 113.1,
      "y": 65.05,
      "z": 1.5,
      "depth": 14.6,
      "shape": "circular",
      "diameter": 5.66,
      "totalLiquidVolume": 100
    },
    "C10": {
      "x": 95.1,
      "y": 56.05,
      "z": 1.5,
      "depth": 14.6,
      "shape": "circular",
      "diameter": 5.66,
      "totalLiquidVolume": 100
    },
    "C11": {
      "x": 104.1,
      "y": 56.05,
      "z": 1.5,
      "depth": 14.6,
      "shape": "circular",
      "diameter": 5.66,
      "totalLiquidVolume": 100
    },
    "C12": {
      "x": 113.1,
      "y": 56.05,
      "z": 1.5,
      "depth": 14.6,
      "shape": "circular",
      "diameter": 5.66,
      "totalLiquidVolume": 100
    },
    "D10": {
      "x": 95.1,
      "y": 47.05,
      "z": 1.5,
      "depth": 14.6,
      "shape": "circular",
      "diameter": 5.66,
      "totalLiquidVolume": 100
    },
    "D11": {
      "x": 104.1,
      "y": 47.05,
      "z": 1.5,
      "depth": 14.6,
      "shape": "circular",
      "diameter": 5.66,
      "totalLiquidVolume": 100
    },
    "D12": {
      "x": 113.1,
      "y": 47.05,
      "z": 1.5,
      "depth": 14.6,
      "shape": "circular",
      "diameter": 5.66,
      "totalLiquidVolume": 100
    },
    "E10": {
      "x": 95.1,
      "y": 38.05,
      "z": 1.5,
      "depth": 14.6,
      "shape": "circular",
      "diameter": 5.66,
      "totalLiquidVolume": 100
    },
    "E11": {
      "x": 104.1,
      "y": 38.05,
      "z": 1.5,
      "depth": 14.6,
      "shape": "circular",
      "diameter": 5.66,
      "totalLiquidVolume": 100
    },
    "E12": {
      "x": 113.1,
      "y": 38.05,
      "z": 1.5,
      "depth": 14.6,
      "shape": "circular",
      "diameter": 5.66,
      "totalLiquidVolume": 100
    },
    "F10": {
      "x": 95.1,
      "y": 29.05,
      "z": 1.5,
      "depth": 14.6,
      "shape": "circular",
      "diameter": 5.66,
      "totalLiquidVolume": 100
    },
    "F11": {
      "x": 104.1,
      "y": 29.05,
      "z": 1.5,
      "depth": 14.6,
      "shape": "circular",
      "diameter": 5.66,
      "totalLiquidVolume": 100
    },
    "F12": {
      "x": 113.1,
      "y": 29.05,
      "z": 1.5,
      "depth": 14.6,
      "shape": "circular",
      "diameter": 5.66,
      "totalLiquidVolume": 100
    },
    "G10": {
      "x": 95.1,
      "y": 20.05,
      "z": 1.5,
      "depth": 14.6,
      "shape": "circular",
      "diameter": 5.66,
      "totalLiquidVolume": 100
    },
    "G11": {
      "x": 104.1,
      "y": 20.05,
      "z": 1.5,
      "depth": 14.6,
      "shape": "circular",
      "diameter": 5.66,
      "totalLiquidVolume": 100
    },
    "G12": {
      "x": 113.1,
      "y": 20.05,
      "z": 1.5,
      "depth": 14.6,
      "shape": "circular",
      "diameter": 5.66,
      "totalLiquidVolume": 100
    },
    "H10": {
      "x": 95.1,
      "y": 11.05,
      "z": 1.5,
      "depth": 14.6,
      "shape": "circular",
      "diameter": 5.66,
      "totalLiquidVolume": 100
    },
    "H11": {
      "x": 104.1,
      "y": 11.05,
      "z": 1.5,
      "depth": 14.6,
      "shape": "circular",
      "diameter": 5.66,
      "totalLiquidVolume": 100
    },
    "H12": {
      "x": 113.1,
      "y": 11.05,
      "z": 1.5,
      "depth": 14.6,
      "shape": "circular",
      "diameter": 5.66,
      "totalLiquidVolume": 100
    }
  },
  "groups": [
    {
      "wells": [
        "A1",
        "B1",
        "C1",
        "D1",
        "E1",
        "F1",
        "G1",
        "H1",
        "A2",
        "B2",
        "C2",
        "D2",
        "E2",
        "F2",
        "G2",
        "H2",
        "A3",
        "B3",
        "C3",
        "D3",
        "E3",
        "F3",
        "G3",
        "H3",
        "A4",
        "B4",
        "C4",
        "D4",
        "E4",
        "F4",
        "G4",
        "H4",
        "A5",
        "B5",
        "C5",
        "D5",
        "E5",
        "F5",
        "G5",
        "H5",
        "A6",
        "B6",
        "C6",
        "D6",
        "E6",
        "F6",
        "G6",
        "H6",
        "A7",
        "B7",
        "C7",
        "D7",
        "E7",
        "F7",
        "G7",
        "H7",
        "A8",
        "B8",
        "C8",
        "D8",
        "E8",
        "F8",
        "G8",
        "H8",
        "A9",
        "B9",
        "C9",
        "D9",
        "E9",
        "F9",
        "G9",
        "H9",
        "A10",
        "B10",
        "C10",
        "D10",
        "E10",
        "F10",
        "G10",
        "H10",
        "A11",
        "B11",
        "C11",
        "D11",
        "E11",
        "F11",
        "G11",
        "H11",
        "A12",
        "B12",
        "C12",
        "D12",
        "E12",
        "F12",
        "G12",
        "H12"
      ],
      "metadata": {
        "wellBottomShape": "v"
      }
    }
  ],
  "offset": {
    "x": 14.1,
    "y": 11.05,
    "z": 14.22
  },
  "version": 1,
  "metadata": {
    "tags": [],
    "displayName": "GSBIO 96 Well Plate 100 µL",
    "displayCategory": "wellPlate",
    "displayVolumeUnits": "µL"
  },
  "ordering": [
    [
      "A1",
      "B1",
      "C1",
      "D1",
      "E1",
      "F1",
      "G1",
      "H1"
    ],
    [
      "A2",
      "B2",
      "C2",
      "D2",
      "E2",
      "F2",
      "G2",
      "H2"
    ],
    [
      "A3",
      "B3",
      "C3",
      "D3",
      "E3",
      "F3",
      "G3",
      "H3"
    ],
    [
      "A4",
      "B4",
      "C4",
      "D4",
      "E4",
      "F4",
      "G4",
      "H4"
    ],
    [
      "A5",
      "B5",
      "C5",
      "D5",
      "E5",
      "F5",
      "G5",
      "H5"
    ],
    [
      "A6",
      "B6",
      "C6",
      "D6",
      "E6",
      "F6",
      "G6",
      "H6"
    ],
    [
      "A7",
      "B7",
      "C7",
      "D7",
      "E7",
      "F7",
      "G7",
      "H7"
    ],
    [
      "A8",
      "B8",
      "C8",
      "D8",
      "E8",
      "F8",
      "G8",
      "H8"
    ],
    [
      "A9",
      "B9",
      "C9",
      "D9",
      "E9",
      "F9",
      "G9",
      "H9"
    ],
    [
      "A10",
      "B10",
      "C10",
      "D10",
      "E10",
      "F10",
      "G10",
      "H10"
    ],
    [
      "A11",
      "B11",
      "C11",
      "D11",
      "E11",
      "F11",
      "G11",
      "H11"
    ],
    [
      "A12",
      "B12",
      "C12",
      "D12",
      "E12",
      "F12",
      "G12",
      "H12"
    ]
  ],
  "namespace": "mgi",
  "dimensions": {
    "xDimension": 127.2,
    "yDimension": 85.1,
    "zDimension": 16.1
  },
  "parameters": {
    "format": "96Standard",
    "quirks": [],
    "loadName": "gsbio_96_wellplate_100ul",
    "isTiprack": false,
    "isMagneticModuleCompatible": true
  },
  "fieldWrappers": [],
  "schemaVersion": 2,
  "cornerOffsetFromSlot": {
    "x": 14.1,
    "y": 11.05,
    "z": 14.22
  },
  "holeToLabwareTopDistance": 0,
  "stackingOffsetWithModule": {},
  "stackingOffsetWithLabware": {
    "mgi_96_pcr_adapter": {
      "x": -1.8,
      "y": 0,
      "z": -5.5
    },
    "mdk_pcrplate_plateadapter_general": {
      "x": -1.0,
      "y": 0,
      "z": -7
    }
  }
}